bernina/__init__.py
bernina/control.py
bernina/db.py
bernina/dbbuild.py
bernina/main.py
bernina/web.py
bernina/yamlparse.py
bernina/data_files/settings/default.ini
bernina/static/ico/favicon.ico
bernina/static/ico/favicon.png
bernina/static/ico/favicon.xcf
bernina/static/js/neopolitan.js
bernina/static/less/grisons.less
bernina/static/less/grisonsfont.less
bernina/static/less/style.less
bernina/static/png/next.png
bernina/static/png/pause.png
bernina/static/png/play.png
bernina/static/png/prev.png
bernina/static/svg/action_refreshmetadata.svg
bernina/static/svg/action_scanlibrary.svg
bernina/static/svg/source.txt
bernina/web/library.pyhp
bernina/web/common/head.html
bernina-0.0.1.dist-info/LICENSE
bernina-0.0.1.dist-info/METADATA
bernina-0.0.1.dist-info/WHEEL
bernina-0.0.1.dist-info/entry_points.txt
bernina-0.0.1.dist-info/top_level.txt
bernina-0.0.1.dist-info/RECORD
